tagmatic/__init__.py
tagmatic/core/__init__.py
tagmatic/core/category.py
tagmatic/core/classifier.py
tagmatic/prompts/__init__.py
tagmatic/prompts/templates.py
tagmatic/providers/__init__.py
tagmatic/providers/base.py
tagmatic/utils/__init__.py
tagmatic/utils/config.py
tagmatic/utils/validation.py
tagmatic-0.1.0.dist-info/METADATA
tagmatic-0.1.0.dist-info/WHEEL
tagmatic-0.1.0.dist-info/licenses/LICENSE
tagmatic-0.1.0.dist-info/RECORD
