Metadata-Version: 2.4
Name: tagmatic
Version: 0.1.0
Summary: Generic text classification library using Large Language Models with user-defined categories
Project-URL: Homepage, https://github.com/tagmatic/tagmatic
Project-URL: Repository, https://github.com/tagmatic/tagmatic
Project-URL: Documentation, https://github.com/tagmatic/tagmatic#readme
Project-URL: Bug Tracker, https://github.com/tagmatic/tagmatic/issues
Author: Tagmatic Contributors
License: MIT
License-File: LICENSE
Keywords: langchain,llm,machine-learning,nlp,text-classification
Classifier: Development Status :: 3 - Alpha
Classifier: Intended Audience :: Developers
Classifier: License :: OSI Approved :: MIT License
Classifier: Programming Language :: Python :: 3
Classifier: Programming Language :: Python :: 3.9
Classifier: Programming Language :: Python :: 3.10
Classifier: Programming Language :: Python :: 3.11
Classifier: Programming Language :: Python :: 3.12
Classifier: Programming Language :: Python :: 3.13
Classifier: Topic :: Scientific/Engineering :: Artificial Intelligence
Classifier: Topic :: Text Processing :: Linguistic
Requires-Python: >=3.9
Requires-Dist: langchain-core>=0.1.0
Requires-Dist: langchain-openai>=0.3.18
Requires-Dist: langchain>=0.1.0
Requires-Dist: pydantic>=2.0.0
Requires-Dist: pytest>=8.3.5
Requires-Dist: python-dotenv>=1.1.0
Requires-Dist: typing-extensions>=4.0.0
Provides-Extra: all
Requires-Dist: black>=23.0.0; extra == 'all'
Requires-Dist: flake8>=6.0.0; extra == 'all'
Requires-Dist: isort>=5.12.0; extra == 'all'
Requires-Dist: langchain-anthropic>=0.1.0; extra == 'all'
Requires-Dist: langchain-openai>=0.1.0; extra == 'all'
Requires-Dist: mypy>=1.0.0; extra == 'all'
Requires-Dist: pre-commit>=3.0.0; extra == 'all'
Requires-Dist: pytest-cov>=4.0.0; extra == 'all'
Requires-Dist: pytest>=7.0.0; extra == 'all'
Provides-Extra: anthropic
Requires-Dist: langchain-anthropic>=0.1.0; extra == 'anthropic'
Provides-Extra: dev
Requires-Dist: black>=23.0.0; extra == 'dev'
Requires-Dist: flake8>=6.0.0; extra == 'dev'
Requires-Dist: isort>=5.12.0; extra == 'dev'
Requires-Dist: mypy>=1.0.0; extra == 'dev'
Requires-Dist: pre-commit>=3.0.0; extra == 'dev'
Requires-Dist: pytest-cov>=4.0.0; extra == 'dev'
Requires-Dist: pytest>=7.0.0; extra == 'dev'
Provides-Extra: openai
Requires-Dist: langchain-openai>=0.1.0; extra == 'openai'
